setup.py
src/tagman/__init__.py
src/tagman/admin.py
src/tagman/models.py
src/tagman.egg-info/PKG-INFO
src/tagman.egg-info/SOURCES.txt
src/tagman.egg-info/dependency_links.txt
src/tagman.egg-info/top_level.txt
src/tagman/migrations/0001_initial.py
src/tagman/migrations/0002_auto__add_field_tag_slug__add_field_taggroup_slug.py
src/tagman/migrations/0003_auto__del_unique_tag_name.py
src/tagman/migrations/0004_auto__add_field_tag_archived__chg_field_tag_group__del_unique_tag_grou.py
src/tagman/migrations/__init__.py
src/tagman/tests/__init__.py
src/tagman/tests/models.py
src/tagman/tests/test_models.py