Metadata-Version: 1.1
Name: tagman
Version: 0.1.11
Summary: Curated tagging app for Django
Home-page: https://github.com/Rethought/tagman.git
Author: ReThought Ltd
Author-email: code@rethought-solutions.com
License: BSD
Keywords: django,tagging,tagman
Platform: UNKNOWN
Classifier: Intended Audience :: Developers
Classifier: License :: OSI Approved :: BSD License
Classifier: Operating System :: OS Independent
Classifier: Programming Language :: Python
